opensearch_dsl/__init__.py
opensearch_dsl/aggs.py
opensearch_dsl/analysis.py
opensearch_dsl/connections.py
opensearch_dsl/document.py
opensearch_dsl/exceptions.py
opensearch_dsl/faceted_search.py
opensearch_dsl/field.py
opensearch_dsl/function.py
opensearch_dsl/index.py
opensearch_dsl/mapping.py
opensearch_dsl/query.py
opensearch_dsl/search.py
opensearch_dsl/serializer.py
opensearch_dsl/update_by_query.py
opensearch_dsl/utils.py
opensearch_dsl/wrappers.py
opensearch_dsl/response/__init__.py
opensearch_dsl/response/aggs.py
opensearch_dsl/response/hit.py
opensearch_dsl-2.1.0.dist-info/AUTHORS
opensearch_dsl-2.1.0.dist-info/LICENSE.txt
opensearch_dsl-2.1.0.dist-info/METADATA
opensearch_dsl-2.1.0.dist-info/NOTICE.txt
opensearch_dsl-2.1.0.dist-info/WHEEL
opensearch_dsl-2.1.0.dist-info/top_level.txt
opensearch_dsl-2.1.0.dist-info/RECORD
