Metadata-Version: 2.1
Name: opensearch-dsl
Version: 2.1.0
Summary: Python client for OpenSearch
Home-page: https://github.com/opensearch-project/opensearch-dsl-py
Author: Honza Král, Guian Gumpac
Author-email: honza.kral@gmail.com, guiang@bitquilltech.com
Maintainer: Charlene Solonynka, Yury Fridlyand, Guian Gumpac
Maintainer-email: charlenes@bitquilltech.com, yuryf@bitquilltech.com, guiang@bitquilltech.com
License: Apache-2.0
Classifier: Development Status :: 5 - Production/Stable
Classifier: License :: OSI Approved :: Apache Software License
Classifier: Intended Audience :: Developers
Classifier: Operating System :: OS Independent
Classifier: Programming Language :: Python
Classifier: Programming Language :: Python :: 2
Classifier: Programming Language :: Python :: 2.7
Classifier: Programming Language :: Python :: 3
Classifier: Programming Language :: Python :: 3.4
Classifier: Programming Language :: Python :: 3.5
Classifier: Programming Language :: Python :: 3.6
Classifier: Programming Language :: Python :: 3.7
Classifier: Programming Language :: Python :: 3.8
Classifier: Programming Language :: Python :: 3.9
Classifier: Programming Language :: Python :: Implementation :: CPython
Classifier: Programming Language :: Python :: Implementation :: PyPy
Requires-Python: >=2.7, !=3.0.*, !=3.1.*, !=3.2.*, !=3.3.*
Provides-Extra: develop
License-File: LICENSE.txt
License-File: NOTICE.txt
License-File: AUTHORS
